MANIFEST.in
README.md
pyproject.toml
setup.py
mercury/__init__.py
mercury/common.py
mercury/demo.py
mercury/exec.py
mercury/exec2.py
mercury/manage.py
mercury/mercury.py
mercury/requirements.txt
mercury/topdf.py
mercury/apps/__init__.py
mercury/apps/notebooks/__init__.py
mercury/apps/notebooks/admin.py
mercury/apps/notebooks/apps.py
mercury/apps/notebooks/models.py
mercury/apps/notebooks/serializers.py
mercury/apps/notebooks/slides_themes.py
mercury/apps/notebooks/tasks.py
mercury/apps/notebooks/tests.py
mercury/apps/notebooks/urls.py
mercury/apps/notebooks/views.py
mercury/apps/notebooks/management/__init__.py
mercury/apps/notebooks/management/commands/__init__.py
mercury/apps/notebooks/management/commands/add.py
mercury/apps/notebooks/management/commands/delete.py
mercury/apps/notebooks/management/commands/list.py
mercury/apps/notebooks/management/commands/watch.py
mercury/apps/notebooks/migrations/0001_initial.py
mercury/apps/notebooks/migrations/__init__.py
mercury/apps/tasks/__init__.py
mercury/apps/tasks/admin.py
mercury/apps/tasks/apps.py
mercury/apps/tasks/clean_service.py
mercury/apps/tasks/export_pdf.py
mercury/apps/tasks/models.py
mercury/apps/tasks/notify.py
mercury/apps/tasks/serializers.py
mercury/apps/tasks/tasks.py
mercury/apps/tasks/tasks_export.py
mercury/apps/tasks/tests.py
mercury/apps/tasks/urls.py
mercury/apps/tasks/views.py
mercury/apps/tasks/migrations/0001_initial.py
mercury/apps/tasks/migrations/__init__.py
mercury/frontend-dist/asset-manifest.json
mercury/frontend-dist/favicon.ico
mercury/frontend-dist/index.html
mercury/frontend-dist/manifest.json
mercury/frontend-dist/mercury_logo.svg
mercury/frontend-dist/robots.txt
mercury/frontend-dist/static/css/2.c6cf5ff9.chunk.css
mercury/frontend-dist/static/css/2.c6cf5ff9.chunk.css.map
mercury/frontend-dist/static/css/main.10b25b9c.chunk.css
mercury/frontend-dist/static/css/main.10b25b9c.chunk.css.map
mercury/frontend-dist/static/js/2.6e058ab1.chunk.js
mljar_mercury.egg-info/PKG-INFO
mljar_mercury.egg-info/SOURCES.txt
mljar_mercury.egg-info/dependency_links.txt
mljar_mercury.egg-info/entry_points.txt
mljar_mercury.egg-info/requires.txt
mljar_mercury.egg-info/top_level.txt