Metadata-Version: 2.1
Name: mljar-mercury
Version: 1.1.6
Summary: Convert Python Notebook to web app and share with non-technical users
Home-page: https://github.com/mljar/mercury
Maintainer: MLJAR Sp. z o.o.
Maintainer-email: contact@mljar.com
License: UNKNOWN
Platform: UNKNOWN
Classifier: Programming Language :: Python :: 3
Classifier: Operating System :: OS Independent
Requires-Python: >=3.7
